pythonzimbra/__init__.py
pythonzimbra/communication.py
pythonzimbra/request.py
pythonzimbra/request_json.py
pythonzimbra/request_xml.py
pythonzimbra/response.py
pythonzimbra/response_json.py
pythonzimbra/response_xml.py
pythonzimbra/exceptions/__init__.py
pythonzimbra/exceptions/auth.py
pythonzimbra/exceptions/communication.py
pythonzimbra/exceptions/request.py
pythonzimbra/tools/__init__.py
pythonzimbra/tools/auth.py
pythonzimbra/tools/dict.py
pythonzimbra/tools/preauth.py
pythonzimbra/tools/urllib2_tls.py
pythonzimbra/tools/xmlserializer.py
python_zimbra-2.4.dist-info/LICENSE
python_zimbra-2.4.dist-info/METADATA
python_zimbra-2.4.dist-info/WHEEL
python_zimbra-2.4.dist-info/top_level.txt
python_zimbra-2.4.dist-info/RECORD
